rsyncstats/__init__.py
rsyncstats-0.1.5.dist-info/LICENSE
rsyncstats-0.1.5.dist-info/METADATA
rsyncstats-0.1.5.dist-info/WHEEL
rsyncstats-0.1.5.dist-info/entry_points.txt
rsyncstats-0.1.5.dist-info/top_level.txt
rsyncstats-0.1.5.dist-info/RECORD
