Metadata-Version: 2.1
Name: rsyncstats
Version: 0.1.5
Summary: Export logs from rsync daemon logs as influxdb timeseries
Home-page: https://github.com/resif/rsyncstats
Author: Jonathan Schaeffer
Author-email: jonathan.schaeffer@univ-grenoble-alpes.fr
Maintainer: Jonathan Schaeffer
Maintainer-email: jonathan.schaeffer@univ-grenoble-alpes.fr
License: GPL-3.0
Platform: UNKNOWN
Classifier: Development Status :: 4 - Beta
Classifier: Intended Audience :: Developers
Classifier: License :: OSI Approved :: GNU General Public License v3 or later (GPLv3+)
Classifier: Natural Language :: English
Classifier: Operating System :: OS Independent
Classifier: Programming Language :: Python :: 3.6
Classifier: Programming Language :: Python :: 3.7
Requires-Dist: Click (==7.0)
Requires-Dist: influxdb (==5.2.1)
Requires-Dist: maxminddb (==1.4.1)
Requires-Dist: maxminddb-geolite2 (==2018.703)
Requires-Dist: regex (==2019.2.7)
Requires-Dist: geohash2
